LICENSE
MANIFEST.in
README.rst
cron.py
cronmon.ini
manage.py
migrate.py
requirements.txt
setup.cfg
setup.py
tox.ini
cronmon/__init__.py
cronmon/email.py
cronmon/exceptions.py
cronmon/models.py
cronmon/utils.py
cronmon/api/__init__.py
cronmon/api/errors.py
cronmon/api/views.py
cronmon/api/api_1_0/__init__.py
cronmon/api/api_1_0/authentication.py
cronmon/api/api_1_0/views.py
cronmon/auth/__init__.py
cronmon/auth/forms.py
cronmon/auth/views.py
cronmon/conf/config.py
cronmon/conf/log.conf
cronmon/main/__init__.py
cronmon/main/errors.py
cronmon/main/forms.py
cronmon/main/taskcyclecheck.py
cronmon/main/views.py
cronmon/static/fonts/msyh.ttf
cronmon/static/fonts/msyhbd.ttf
cronmon/static/images/bizAdmin.jpg
cronmon/static/images/favicon.ico
cronmon/static/images/superAdmin.jpg
cronmon/static/plugins/adminlte/css/AdminLTE.css
cronmon/static/plugins/adminlte/css/AdminLTE.min.css
cronmon/static/plugins/adminlte/css/adminlte.css.map
cronmon/static/plugins/adminlte/css/adminlte.min.css.map
cronmon/static/plugins/adminlte/css/alt/AdminLTE-bootstrap-social.css
cronmon/static/plugins/adminlte/css/alt/AdminLTE-bootstrap-social.min.css
cronmon/static/plugins/adminlte/css/alt/AdminLTE-fullcalendar.css
cronmon/static/plugins/adminlte/css/alt/AdminLTE-fullcalendar.min.css
cronmon/static/plugins/adminlte/css/alt/AdminLTE-select2.css
cronmon/static/plugins/adminlte/css/alt/AdminLTE-select2.min.css
cronmon/static/plugins/adminlte/css/alt/AdminLTE-without-plugins.css
cronmon/static/plugins/adminlte/css/alt/AdminLTE-without-plugins.min.css
cronmon/static/plugins/adminlte/css/skins/_all-skins.css
cronmon/static/plugins/adminlte/css/skins/_all-skins.min.css
cronmon/static/plugins/adminlte/css/skins/skin-black-light.css
cronmon/static/plugins/adminlte/css/skins/skin-black-light.min.css
cronmon/static/plugins/adminlte/css/skins/skin-black.css
cronmon/static/plugins/adminlte/css/skins/skin-black.min.css
cronmon/static/plugins/adminlte/css/skins/skin-blue-light.css
cronmonweb.egg-info/PKG-INFO
cronmonweb.egg-info/SOURCES.txt
cronmonweb.egg-info/dependency_links.txt
cronmonweb.egg-info/not-zip-safe
cronmonweb.egg-info/requires.txt
cronmonweb.egg-info/top_level.txt
